honor_mcp/__init__.py
honor_mcp/cli.py
honor_mcp/config.py
honor_mcp/server.py
honor_mcp/utils.py
honor_mcp-0.1.0.dist-info/METADATA
honor_mcp-0.1.0.dist-info/WHEEL
honor_mcp-0.1.0.dist-info/entry_points.txt
honor_mcp-0.1.0.dist-info/top_level.txt
honor_mcp-0.1.0.dist-info/RECORD
