Metadata-Version: 2.4
Name: honor-mcp
Version: 0.1.0
Summary: MCP server for interacting with Honor Platform API
Author-email: Brian Steele <brian@honor.education>
License-Expression: MIT
Project-URL: Homepage, https://github.com/HonorEd-Technologies/honor-mcp
Project-URL: Bug Tracker, https://github.com/HonorEd-Technologies/honor-mcp/issues
Classifier: Programming Language :: Python :: 3
Classifier: Programming Language :: Python :: 3.10
Classifier: Operating System :: OS Independent
Requires-Python: >=3.10
Requires-Dist: httpx>=0.28.1
Requires-Dist: mcp[cli]>=1.7.1
Requires-Dist: twine>=6.1.0
Provides-Extra: dev
Requires-Dist: ruff>=0.6.0; extra == "dev"
